pythomate/__init__.py
pythomate/cli.py
pythomate/power_automate.py
pythomate-0.6.dist-info/LICENCE.txt
pythomate-0.6.dist-info/METADATA
pythomate-0.6.dist-info/WHEEL
pythomate-0.6.dist-info/entry_points.txt
pythomate-0.6.dist-info/top_level.txt
pythomate-0.6.dist-info/RECORD
