Metadata-Version: 2.1
Name: pythomate
Version: 0.6
Summary: Automatiza acionamento de fluxos Power Automate.
Home-page: https://github.com/lab-mg/pythomate
Author: Diretoria Central de Desburocratização - DCD/SUGES/SEPLAG - Automatiza.MG
Author-email: simplificacao@planejamento.mg.gov.br
License: UNKNOWN
Keywords: python,power automate,automate,automação
Platform: UNKNOWN
Classifier: Development Status :: 1 - Planning
Classifier: Intended Audience :: Developers
Classifier: Programming Language :: Python :: 3
Classifier: Operating System :: Microsoft :: Windows
License-File: LICENCE.txt
Requires-Dist: click ==8.1.7
Requires-Dist: pywinauto ==0.6.8
